amazon_codeguru_jupyterlab_extension/__init__.py
amazon_codeguru_jupyterlab_extension/_version.py
amazon_codeguru_jupyterlab_extension/cfg.py
amazon_codeguru_jupyterlab_extension/codeguru.py
amazon_codeguru_jupyterlab_extension/constants.py
amazon_codeguru_jupyterlab_extension/diagnostics.py
amazon_codeguru_jupyterlab_extension/parseNotebookIntoScript.py
amazon_codeguru_jupyterlab_extension/plugin.py
amazon_codeguru_jupyterlab_extension-1.1.0.data/data/share/jupyter/labextensions/@aws/amazon-codeguru-extension/build_log.json
amazon_codeguru_jupyterlab_extension-1.1.0.data/data/share/jupyter/labextensions/@aws/amazon-codeguru-extension/install.json
amazon_codeguru_jupyterlab_extension-1.1.0.data/data/share/jupyter/labextensions/@aws/amazon-codeguru-extension/package.json
amazon_codeguru_jupyterlab_extension-1.1.0.data/data/share/jupyter/labextensions/@aws/amazon-codeguru-extension/schemas/@aws/amazon-codeguru-extension/package.json.orig
amazon_codeguru_jupyterlab_extension-1.1.0.data/data/share/jupyter/labextensions/@aws/amazon-codeguru-extension/schemas/@aws/amazon-codeguru-extension/plugin.json
amazon_codeguru_jupyterlab_extension-1.1.0.data/data/share/jupyter/labextensions/@aws/amazon-codeguru-extension/static/lib_index_js-webpack_sharing_consume_default_jupyterlab_coreutils.c4c5385e7a8c0c90533a.js
amazon_codeguru_jupyterlab_extension-1.1.0.data/data/share/jupyter/labextensions/@aws/amazon-codeguru-extension/static/lib_index_js-webpack_sharing_consume_default_jupyterlab_coreutils.c4c5385e7a8c0c90533a.js.map
amazon_codeguru_jupyterlab_extension-1.1.0.data/data/share/jupyter/labextensions/@aws/amazon-codeguru-extension/static/node_modules_cloudscape-design_global-styles_dist_index_js.49bd81ccb2dba12e6001.js
amazon_codeguru_jupyterlab_extension-1.1.0.data/data/share/jupyter/labextensions/@aws/amazon-codeguru-extension/static/node_modules_cloudscape-design_global-styles_dist_index_js.49bd81ccb2dba12e6001.js.map
amazon_codeguru_jupyterlab_extension-1.1.0.dist-info/METADATA
amazon_codeguru_jupyterlab_extension-1.1.0.dist-info/WHEEL
amazon_codeguru_jupyterlab_extension-1.1.0.dist-info/entry_points.txt
amazon_codeguru_jupyterlab_extension-1.1.0.dist-info/licenses/LICENSE
amazon_codeguru_jupyterlab_extension-1.1.0.dist-info/licenses/NOTICE
amazon_codeguru_jupyterlab_extension-1.1.0.dist-info/RECORD
