Metadata-Version: 2.1
Name: amazon_codeguru_jupyterlab_extension
Version: 1.1.0
Summary: Security, code quality, and ML recommendations
Project-URL: Homepage, https://github.com/aws/amazon-codeguru-jupyterlab-extension
Project-URL: Bug Tracker, https://github.com/aws/amazon-codeguru-jupyterlab-extension/issues
Project-URL: Repository, https://github.com/aws/amazon-codeguru-jupyterlab-extension.git
License-File: LICENSE
License-File: NOTICE
Classifier: Framework :: Jupyter
Classifier: Framework :: Jupyter :: JupyterLab
Classifier: Framework :: Jupyter :: JupyterLab :: 3
Classifier: Framework :: Jupyter :: JupyterLab :: Extensions
Classifier: Framework :: Jupyter :: JupyterLab :: Extensions :: Prebuilt
Classifier: License :: OSI Approved :: BSD License
Classifier: Programming Language :: Python
Classifier: Programming Language :: Python :: 3
Classifier: Programming Language :: Python :: 3.7
Classifier: Programming Language :: Python :: 3.8
Classifier: Programming Language :: Python :: 3.9
Classifier: Programming Language :: Python :: 3.10
Classifier: Programming Language :: Python :: 3.11
Requires-Python: >=3.7
Requires-Dist: boto3>=1.26.162
Requires-Dist: jupyterlab-lsp>=4.0.0
Requires-Dist: python-lsp-server<=1.7.1
Provides-Extra: dev
Requires-Dist: build; extra == 'dev'
Requires-Dist: hatch; extra == 'dev'
Requires-Dist: twine; extra == 'dev'
Provides-Extra: tests
Requires-Dist: coverage; extra == 'tests'
Requires-Dist: pytest; extra == 'tests'
